BoBaFor/BoBaFor.yml
BoBaFor/GWAS.yml
BoBaFor/Snakefile
BoBaFor/__init__.py
BoBaFor/main.py
BoBaFor/FeatureSelect/ClassFeatureSelection.py
BoBaFor/FeatureSelect/__init__.py
BoBaFor/TreeTune/ClassIndexing.py
BoBaFor/TreeTune/ClassParamAnalysis.py
BoBaFor/TreeTune/ClassTuning.py
BoBaFor/TreeTune/__init__.py
BoBaFor/scripts/ConfigGenerator.py
BoBaFor/scripts/GWAS_PreFilter_script0.py
BoBaFor/scripts/GWAS_Ranking_script4.py
BoBaFor/scripts/GWAS_ReTuning_script3.py
BoBaFor/scripts/GWAS_Selection_script2.py
BoBaFor/scripts/GWAS_Tuning_script1.py
BoBaFor/scripts/__init__.py
bobafor-0.0.9.dist-info/licenses/LICENSE
bobafor-0.0.9.dist-info/METADATA
bobafor-0.0.9.dist-info/WHEEL
bobafor-0.0.9.dist-info/entry_points.txt
bobafor-0.0.9.dist-info/top_level.txt
bobafor-0.0.9.dist-info/RECORD
