Metadata-Version: 2.4
Name: BoBaFor
Version: 0.0.9
Summary: A machine learning approach for conducting genome wide association studies (GWAS) on bacteria
Home-page: https://github.com/PaulDanPhillips/BoBaFor
Author: Paul Phillips
License: MIT
Requires-Python: ==3.11.10
License-File: LICENSE
Requires-Dist: pandas
Requires-Dist: scipy
Requires-Dist: statsmodels
Requires-Dist: numpy==1.23.5
Requires-Dist: scikit-learn
Requires-Dist: xgboost
Requires-Dist: matplotlib
Requires-Dist: snakemake
Requires-Dist: Boruta
Requires-Dist: shap
Requires-Dist: seaborn
Requires-Dist: plotnine
Requires-Dist: pytest
Dynamic: author
Dynamic: home-page
Dynamic: license
Dynamic: license-file
Dynamic: requires-dist
Dynamic: requires-python
Dynamic: summary
